README.md
pyproject.toml
merge_insertion/__init__.py
merge_insertion.egg-info/PKG-INFO
merge_insertion.egg-info/SOURCES.txt
merge_insertion.egg-info/dependency_links.txt
merge_insertion.egg-info/top_level.txt
tests/test_merge_insertion.py