Metadata-Version: 2.4
Name: merge-insertion
Version: 1.1.0
Summary: The merge-insertion sort (aka the Ford-Johnson algorithm) is optimized for using few comparisons.
Author-email: Hauke Dämpfling <haukex@zero-g.net>
Project-URL: Repository, https://github.com/haukex/merge-insertion.py
Project-URL: Bug Tracker, https://github.com/haukex/merge-insertion.py/issues
Classifier: Programming Language :: Python :: 3
Classifier: Programming Language :: Python :: 3.10
Classifier: Programming Language :: Python :: 3.11
Classifier: Programming Language :: Python :: 3.12
Classifier: Programming Language :: Python :: 3.13
Classifier: Programming Language :: Python :: 3.14
Classifier: License :: OSI Approved :: ISC License (ISCL)
Classifier: Development Status :: 5 - Production/Stable
Classifier: Topic :: Software Development :: Libraries
Requires-Python: >=3.10
